AUTHORS
ChangeLog
LICENSE
MANIFEST.in
README.rst
requirements.txt
setup.cfg
setup.py
leonardo_oembed/__init__.py
leonardo_oembed/models.py
leonardo_oembed.egg-info/PKG-INFO
leonardo_oembed.egg-info/SOURCES.txt
leonardo_oembed.egg-info/dependency_links.txt
leonardo_oembed.egg-info/not-zip-safe
leonardo_oembed.egg-info/pbr.json
leonardo_oembed.egg-info/requires.txt
leonardo_oembed.egg-info/top_level.txt
leonardo_oembed/templates/widget/feed/default.html
leonardo_oembed/templates/widget/oembed/default.html
leonardo_oembed/templates/widget/oembed/photo.html
leonardo_oembed/widget/__init__.py
leonardo_oembed/widget/feed/__init__.py
leonardo_oembed/widget/feed/models.py
leonardo_oembed/widget/oembed/__init__.py
leonardo_oembed/widget/oembed/models.py